jupyter_nbrequirements/__about__.py
jupyter_nbrequirements/__init__.py
jupyter_nbrequirements/magic_parser.py
jupyter_nbrequirements/static/extension.js
jupyter_nbrequirements/static/index.js
jupyter_nbrequirements-0.7.3.data/data/etc/jupyter/nbconfig/notebook.d/jupyter-nbrequirements.json
jupyter_nbrequirements-0.7.3.data/data/share/jupyter/nbextensions/jupyter-nbrequirements/extension.js
jupyter_nbrequirements-0.7.3.data/data/share/jupyter/nbextensions/jupyter-nbrequirements/index.js
jupyter_nbrequirements-0.7.3.dist-info/LICENSE
jupyter_nbrequirements-0.7.3.dist-info/METADATA
jupyter_nbrequirements-0.7.3.dist-info/WHEEL
jupyter_nbrequirements-0.7.3.dist-info/top_level.txt
jupyter_nbrequirements-0.7.3.dist-info/RECORD
